{
	"ImportPath": "hellochat",
	"GoVersion": "go1.6",
	"GodepVersion": "v79",
	"Deps": [
		{
			"ImportPath": "github.com/codegangsta/cli",
			"Comment": "v1.19.1-28-g8ba6f23",
			"Rev": "8ba6f23b6e36d03666a14bd9421f5e3efcb59aca"
		},
		{
			"ImportPath": "github.com/codegangsta/negroni",
			"Comment": "v0.2.0-104-gc0db5fe",
			"Rev": "c0db5feaa33826cd5117930c8f4ee5c0f565eec6"
		},
		{
			"ImportPath": "github.com/elazarl/go-bindata-assetfs",
			"Rev": "30f82fa23fd844bd5bb1e5f216db87fd77b5eb43"
		},
		{
			"ImportPath": "github.com/gorilla/context",
			"Comment": "v1.1-7-g08b5f42",
			"Rev": "08b5f424b9271eedf6f9f0ce86cb9396ed337a42"
		},
		{
			"ImportPath": "github.com/gorilla/mux",
			"Comment": "v1.3.0-5-g599cba5",
			"Rev": "599cba5e7b6137d46ddf58fb1765f5d928e69604"
		},
		{
			"ImportPath": "github.com/gorilla/websocket",
			"Comment": "v1.1.0-29-ga91eba7",
			"Rev": "a91eba7f97777409bc2c443f5534d41dd20c5720"
		},
		{
			"ImportPath": "github.com/rs/cors",
			"Comment": "v1.0",
			"Rev": "a62a804a8a009876ca59105f7899938a1349f4b3"
		},
		{
			"ImportPath": "github.com/rs/xhandler",
			"Comment": "v1.0-1-ged27b6f",
			"Rev": "ed27b6fd65218132ee50cd95f38474a3d8a2cd12"
		},
		{
			"ImportPath": "github.com/txthinking/lawsroom/signal",
			"Rev": "bdd9a50d8f96be70f2ce0e36a17f12dc6717bf4a"
		},
		{
			"ImportPath": "golang.org/x/net/context",
			"Rev": "d1e1b351919c6738fdeb9893d5c998b161464f0c"
		}
	]
}
